p2x_corporate_engine/__init__.py
p2x_corporate_engine/engine.py
p2x_corporate_engine/language_mapping.py
p2x_corporate_engine/pipeline.py
p2x_corporate_engine/server_fast_api.py
p2x_corporate_engine-0.0.5.dist-info/LICENSE
p2x_corporate_engine-0.0.5.dist-info/METADATA
p2x_corporate_engine-0.0.5.dist-info/WHEEL
p2x_corporate_engine-0.0.5.dist-info/RECORD
